{
  "name": "dat_5",
  "data": [
    {
      "pos": {
        "x": 175.88,
        "y": 85.88
      },
      "beta": 4.6674
    },
    {
      "pos": {
        "x": 394.74,
        "y": 27.7
      },
      "beta": 1.1916
    },
    {
      "pos": {
        "x": 391.36,
        "y": 74.35
      },
      "beta": 1.7288
    },
    {
      "pos": {
        "x": 272.31,
        "y": 31.56
      },
      "beta": 3.4422
    },
    {
      "pos": {
        "x": 188.1,
        "y": 65.02
      },
      "beta": 1.4015
    },
    {
      "pos": {
        "x": 346.23,
        "y": 69.72
      },
      "beta": 4.9554
    },
    {
      "pos": {
        "x": 141.46,
        "y": 3.9
      },
      "beta": 0.1331
    },
    {
      "pos": {
        "x": 127.28,
        "y": 71.72
      },
      "beta": 0.6494
    },
    {
      "pos": {
        "x": 445.83,
        "y": 81.6
      },
      "beta": 0.555
    },
    {
      "pos": {
        "x": 106.58,
        "y": 1.7
      },
      "beta": 2.7223
    },
    {
      "pos": {
        "x": 188.91,
        "y": 60.56
      },
      "beta": 0.5524
    },
    {
      "pos": {
        "x": 492.98,
        "y": 23.24
      },
      "beta": 2.5018
    },
    {
      "pos": {
        "x": 161.32,
        "y": 68.39
      },
      "beta": 1.568
    },
    {
      "pos": {
        "x": 285.33,
        "y": 2.29
      },
      "beta": 2.4658
    },
    {
      "pos": {
        "x": 363.15,
        "y": 67.85
      },
      "beta": 4.9843
    },
    {
      "pos": {
        "x": 482.49,
        "y": 8.39
      },
      "beta": 3.5636
    },
    {
      "pos": {
        "x": 85.44,
        "y": 49.3
      },
      "beta": 2.9602
    },
    {
      "pos": {
        "x": 150.88,
        "y": 69.21
      },
      "beta": 4.0306
    },
    {
      "pos": {
        "x": 363.3,
        "y": 44.14
      },
      "beta": 0.2564
    },
    {
      "pos": {
        "x": 236.98,
        "y": 75.49
      },
      "beta": 0.3543
    },
    {
      "pos": {
        "x": 274.06,
        "y": 21.37
      },
      "beta": 5.4982
    },
    {
      "pos": {
        "x": 445.49,
        "y": 1.57
      },
      "beta": 4.4806
    },
    {
      "pos": {
        "x": 320.56,
        "y": 9.31
      },
      "beta": 3.0442
    },
    {
      "pos": {
        "x": 103.01,
        "y": 31.83
      },
      "beta": 0.9803
    },
    {
      "pos": {
        "x": 115.58,
        "y": 55.11
      },
      "beta": 4.5188
    },
    {
      "pos": {
        "x": 256.88,
        "y": 12.9
      },
      "beta": 0.4973
    },
    {
      "pos": {
        "x": 53.95,
        "y": 21.83
      },
      "beta": 1.7449
    },
    {
      "pos": {
        "x": 61.53,
        "y": 73.13
      },
      "beta": 3.7717
    },
    {
      "pos": {
        "x": 5.1,
        "y": 8.38
      },
      "beta": 3.1212
    },
    {
      "pos": {
        "x": 14.83,
        "y": 77.7
      },
      "beta": 4.5796
    },
    {
      "pos": {
        "x": 75.17,
        "y": 96.77
      },
      "beta": 5.4934
    },
    {
      "pos": {
        "x": 90.83,
        "y": 54.83
      },
      "beta": 3.3568
    },
    {
      "pos": {
        "x": 150.53,
        "y": 77.95
      },
      "beta": 5.9473
    },
    {
      "pos": {
        "x": 186.36,
        "y": 16.47
      },
      "beta": 6.0273
    },
    {
      "pos": {
        "x": 25.34,
        "y": 64.79
      },
      "beta": 1.653
    },
    {
      "pos": {
        "x": 93.53,
        "y": 83.0
      },
      "beta": 0.1992
    },
    {
      "pos": {
        "x": 16.06,
        "y": 94.98
      },
      "beta": 5.5175
    },
    {
      "pos": {
        "x": 461.1,
        "y": 70.17
      },
      "beta": 3.6668
    },
    {
      "pos": {
        "x": 236.31,
        "y": 87.26
      },
      "beta": 4.9482
    },
    {
      "pos": {
        "x": 350.23,
        "y": 16.72
      },
      "beta": 2.7587
    },
    {
      "pos": {
        "x": 407.18,
        "y": 46.61
      },
      "beta": 4.2389
    },
    {
      "pos": {
        "x": 415.19,
        "y": 13.63
      },
      "beta": 5.6123
    },
    {
      "pos": {
        "x": 146.04,
        "y": 93.59
      },
      "beta": 4.8527
    },
    {
      "pos": {
        "x": 363.85,
        "y": 58.52
      },
      "beta": 2.5224
    },
    {
      "pos": {
        "x": 330.63,
        "y": 13.67
      },
      "beta": 4.8796
    },
    {
      "pos": {
        "x": 468.34,
        "y": 0.03
      },
      "beta": 2.7819
    },
    {
      "pos": {
        "x": 398.88,
        "y": 43.39
      },
      "beta": 0.9914
    },
    {
      "pos": {
        "x": 103.35,
        "y": 0.27
      },
      "beta": 0.0961
    },
    {
      "pos": {
        "x": 163.67,
        "y": 68.07
      },
      "beta": 0.1013
    },
    {
      "pos": {
        "x": 286.98,
        "y": 11.71
      },
      "beta": 2.4585
    },
    {
      "pos": {
        "x": 488.41,
        "y": 39.23
      },
      "beta": 0.6369
    },
    {
      "pos": {
        "x": 425.62,
        "y": 76.76
      },
      "beta": 0.7261
    },
    {
      "pos": {
        "x": 423.68,
        "y": 51.61
      },
      "beta": 0.71
    },
    {
      "pos": {
        "x": 187.35,
        "y": 14.11
      },
      "beta": 5.6875
    },
    {
      "pos": {
        "x": 385.25,
        "y": 99.0
      },
      "beta": 0.1336
    },
    {
      "pos": {
        "x": 299.66,
        "y": 81.53
      },
      "beta": 0.9285
    },
    {
      "pos": {
        "x": 173.49,
        "y": 66.35
      },
      "beta": 0.9403
    },
    {
      "pos": {
        "x": 266.93,
        "y": 44.16
      },
      "beta": 5.9302
    },
    {
      "pos": {
        "x": 312.38,
        "y": 23.36
      },
      "beta": 0.0561
    },
    {
      "pos": {
        "x": 27.67,
        "y": 97.9
      },
      "beta": 6.1366
    },
    {
      "pos": {
        "x": 473.17,
        "y": 27.07
      },
      "beta": 5.0817
    },
    {
      "pos": {
        "x": 219.84,
        "y": 85.51
      },
      "beta": 5.6944
    },
    {
      "pos": {
        "x": 55.11,
        "y": 29.91
      },
      "beta": 2.2564
    },
    {
      "pos": {
        "x": 397.96,
        "y": 42.04
      },
      "beta": 0.4059
    },
    {
      "pos": {
        "x": 494.08,
        "y": 7.8
      },
      "beta": 1.0088
    },
    {
      "pos": {
        "x": 477.01,
        "y": 19.71
      },
      "beta": 2.6284
    },
    {
      "pos": {
        "x": 215.35,
        "y": 47.71
      },
      "beta": 5.6853
    },
    {
      "pos": {
        "x": 405.94,
        "y": 92.93
      },
      "beta": 5.7418
    },
    {
      "pos": {
        "x": 298.12,
        "y": 5.96
      },
      "beta": 2.2224
    },
    {
      "pos": {
        "x": 132.86,
        "y": 16.39
      },
      "beta": 3.9932
    },
    {
      "pos": {
        "x": 43.68,
        "y": 57.88
      },
      "beta": 0.6904
    },
    {
      "pos": {
        "x": 19.28,
        "y": 28.94
      },
      "beta": 4.1801
    },
    {
      "pos": {
        "x": 122.54,
        "y": 66.4
      },
      "beta": 5.9725
    },
    {
      "pos": {
        "x": 442.24,
        "y": 36.94
      },
      "beta": 5.2901
    },
    {
      "pos": {
        "x": 376.73,
        "y": 65.63
      },
      "beta": 5.3109
    },
    {
      "pos": {
        "x": 204.33,
        "y": 81.56
      },
      "beta": 1.8686
    },
    {
      "pos": {
        "x": 321.72,
        "y": 39.92
      },
      "beta": 4.233
    },
    {
      "pos": {
        "x": 186.54,
        "y": 79.15
      },
      "beta": 0.4669
    },
    {
      "pos": {
        "x": 121.54,
        "y": 7.62
      },
      "beta": 1.4639
    },
    {
      "pos": {
        "x": 413.8,
        "y": 88.61
      },
      "beta": 6.2434
    },
    {
      "pos": {
        "x": 77.37,
        "y": 60.58
      },
      "beta": 6.0205
    },
    {
      "pos": {
        "x": 388.52,
        "y": 84.52
      },
      "beta": 0.3908
    },
    {
      "pos": {
        "x": 240.11,
        "y": 62.47
      },
      "beta": 5.9862
    },
    {
      "pos": {
        "x": 251.75,
        "y": 22.12
      },
      "beta": 4.7834
    },
    {
      "pos": {
        "x": 114.15,
        "y": 33.21
      },
      "beta": 0.5182
    },
    {
      "pos": {
        "x": 209.81,
        "y": 22.05
      },
      "beta": 2.3084
    },
    {
      "pos": {
        "x": 32.42,
        "y": 41.3
      },
      "beta": 0.7773
    },
    {
      "pos": {
        "x": 107.8,
        "y": 58.68
      },
      "beta": 4.0288
    },
    {
      "pos": {
        "x": 289.07,
        "y": 48.51
      },
      "beta": 3.4456
    },
    {
      "pos": {
        "x": 125.35,
        "y": 19.12
      },
      "beta": 2.2104
    },
    {
      "pos": {
        "x": 411.67,
        "y": 98.53
      },
      "beta": 4.1546
    },
    {
      "pos": {
        "x": 214.97,
        "y": 28.22
      },
      "beta": 4.0311
    },
    {
      "pos": {
        "x": 199.44,
        "y": 86.14
      },
      "beta": 2.5523
    },
    {
      "pos": {
        "x": 38.49,
        "y": 3.47
      },
      "beta": 1.7748
    },
    {
      "pos": {
        "x": 278.77,
        "y": 71.24
      },
      "beta": 2.0745
    },
    {
      "pos": {
        "x": 101.4,
        "y": 76.3
      },
      "beta": 3.8029
    },
    {
      "pos": {
        "x": 223.78,
        "y": 18.52
      },
      "beta": 5.9055
    },
    {
      "pos": {
        "x": 394.45,
        "y": 47.1
      },
      "beta": 4.479
    },
    {
      "pos": {
        "x": 341.65,
        "y": 2.02
      },
      "beta": 2.6874
    },
    {
      "pos": {
        "x": 466.03,
        "y": 15.37
      },
      "beta": 4.8249
    },
    {
      "pos": {
        "x": 151.56,
        "y": 7.93
      },
      "beta": 3.9115
    },
    {
      "pos": {
        "x": 243.03,
        "y": 33.57
      },
      "beta": 5.5789
    },
    {
      "pos": {
        "x": 56.9,
        "y": 70.11
      },
      "beta": 1.4895
    },
    {
      "pos": {
        "x": 85.28,
        "y": 20.47
      },
      "beta": 3.1375
    },
    {
      "pos": {
        "x": 297.34,
        "y": 21.48
      },
      "beta": 0.5202
    },
    {
      "pos": {
        "x": 50.87,
        "y": 27.51
      },
      "beta": 3.2258
    },
    {
      "pos": {
        "x": 86.55,
        "y": 78.55
      },
      "beta": 6.2205
    },
    {
      "pos": {
        "x": 163.06,
        "y": 86.37
      },
      "beta": 3.062
    },
    {
      "pos": {
        "x": 18.67,
        "y": 37.67
      },
      "beta": 2.645
    },
    {
      "pos": {
        "x": 445.46,
        "y": 58.53
      },
      "beta": 3.5739
    },
    {
      "pos": {
        "x": 467.02,
        "y": 79.62
      },
      "beta": 3.981
    },
    {
      "pos": {
        "x": 389.55,
        "y": 64.92
      },
      "beta": 1.6155
    },
    {
      "pos": {
        "x": 383.48,
        "y": 38.42
      },
      "beta": 2.3685
    },
    {
      "pos": {
        "x": 473.03,
        "y": 2.63
      },
      "beta": 3.7052
    },
    {
      "pos": {
        "x": 61.09,
        "y": 63.88
      },
      "beta": 1.2299
    },
    {
      "pos": {
        "x": 186.44,
        "y": 1.78
      },
      "beta": 3.2885
    },
    {
      "pos": {
        "x": 196.66,
        "y": 51.82
      },
      "beta": 5.7506
    },
    {
      "pos": {
        "x": 441.89,
        "y": 5.12
      },
      "beta": 2.0744
    },
    {
      "pos": {
        "x": 470.39,
        "y": 53.43
      },
      "beta": 2.855
    },
    {
      "pos": {
        "x": 61.31,
        "y": 0.6
      },
      "beta": 4.8327
    },
    {
      "pos": {
        "x": 353.88,
        "y": 59.28
      },
      "beta": 4.2502
    },
    {
      "pos": {
        "x": 265.0,
        "y": 19.37
      },
      "beta": 1.7476
    },
    {
      "pos": {
        "x": 383.14,
        "y": 56.75
      },
      "beta": 1.6922
    },
    {
      "pos": {
        "x": 457.08,
        "y": 39.53
      },
      "beta": 5.1297
    },
    {
      "pos": {
        "x": 345.48,
        "y": 11.48
      },
      "beta": 6.2508
    },
    {
      "pos": {
        "x": 239.47,
        "y": 81.05
      },
      "beta": 3.8007
    },
    {
      "pos": {
        "x": 252.39,
        "y": 70.78
      },
      "beta": 5.5973
    },
    {
      "pos": {
        "x": 319.3,
        "y": 53.63
      },
      "beta": 3.0672
    },
    {
      "pos": {
        "x": 68.21,
        "y": 92.39
      },
      "beta": 1.3211
    },
    {
      "pos": {
        "x": 277.38,
        "y": 53.78
      },
      "beta": 1.213
    },
    {
      "pos": {
        "x": 176.08,
        "y": 27.65
      },
      "beta": 1.8143
    },
    {
      "pos": {
        "x": 139.32,
        "y": 48.03
      },
      "beta": 5.4246
    },
    {
      "pos": {
        "x": 205.85,
        "y": 69.13
      },
      "beta": 2.9178
    },
    {
      "pos": {
        "x": 77.05,
        "y": 33.25
      },
      "beta": 0.9653
    },
    {
      "pos": {
        "x": 390.06,
        "y": 54.28
      },
      "beta": 1.447
    },
    {
      "pos": {
        "x": 238.32,
        "y": 89.42
      },
      "beta": 2.1221
    },
    {
      "pos": {
        "x": 413.88,
        "y": 17.57
      },
      "beta": 5.9844
    },
    {
      "pos": {
        "x": 297.75,
        "y": 59.89
      },
      "beta": 1.4941
    },
    {
      "pos": {
        "x": 245.43,
        "y": 39.35
      },
      "beta": 3.0403
    },
    {
      "pos": {
        "x": 70.63,
        "y": 44.46
      },
      "beta": 3.117
    },
    {
      "pos": {
        "x": 31.32,
        "y": 72.47
      },
      "beta": 3.8569
    },
    {
      "pos": {
        "x": 15.42,
        "y": 28.98
      },
      "beta": 3.6438
    },
    {
      "pos": {
        "x": 277.94,
        "y": 7.08
      },
      "beta": 0.1652
    },
    {
      "pos": {
        "x": 296.89,
        "y": 34.18
      },
      "beta": 1.9738
    },
    {
      "pos": {
        "x": 37.21,
        "y": 24.25
      },
      "beta": 2.1699
    },
    {
      "pos": {
        "x": 7.88,
        "y": 99.43
      },
      "beta": 6.1111
    },
    {
      "pos": {
        "x": 21.43,
        "y": 40.8
      },
      "beta": 3.5281
    },
    {
      "pos": {
        "x": 296.67,
        "y": 72.41
      },
      "beta": 0.4169
    },
    {
      "pos": {
        "x": 151.07,
        "y": 60.88
      },
      "beta": 3.589
    },
    {
      "pos": {
        "x": 326.6,
        "y": 92.29
      },
      "beta": 4.6853
    },
    {
      "pos": {
        "x": 160.89,
        "y": 18.75
      },
      "beta": 2.7848
    },
    {
      "pos": {
        "x": 238.99,
        "y": 48.76
      },
      "beta": 2.3664
    },
    {
      "pos": {
        "x": 176.18,
        "y": 44.62
      },
      "beta": 1.0401
    },
    {
      "pos": {
        "x": 324.49,
        "y": 93.38
      },
      "beta": 5.3977
    },
    {
      "pos": {
        "x": 81.93,
        "y": 87.13
      },
      "beta": 5.8469
    },
    {
      "pos": {
        "x": 382.9,
        "y": 87.85
      },
      "beta": 4.5396
    },
    {
      "pos": {
        "x": 487.47,
        "y": 28.4
      },
      "beta": 1.9985
    },
    {
      "pos": {
        "x": 226.22,
        "y": 8.36
      },
      "beta": 3.2058
    },
    {
      "pos": {
        "x": 212.03,
        "y": 38.35
      },
      "beta": 4.8974
    },
    {
      "pos": {
        "x": 438.43,
        "y": 69.46
      },
      "beta": 0.157
    },
    {
      "pos": {
        "x": 344.78,
        "y": 58.32
      },
      "beta": 3.4702
    },
    {
      "pos": {
        "x": 360.06,
        "y": 12.19
      },
      "beta": 1.9259
    },
    {
      "pos": {
        "x": 490.33,
        "y": 63.48
      },
      "beta": 1.7243
    },
    {
      "pos": {
        "x": 422.93,
        "y": 50.82
      },
      "beta": 0.2995
    },
    {
      "pos": {
        "x": 462.49,
        "y": 40.11
      },
      "beta": 0.9197
    },
    {
      "pos": {
        "x": 367.16,
        "y": 1.76
      },
      "beta": 0.3444
    },
    {
      "pos": {
        "x": 434.9,
        "y": 68.02
      },
      "beta": 1.6457
    },
    {
      "pos": {
        "x": 366.71,
        "y": 77.28
      },
      "beta": 2.075
    },
    {
      "pos": {
        "x": 395.35,
        "y": 45.17
      },
      "beta": 4.64
    },
    {
      "pos": {
        "x": 334.11,
        "y": 78.69
      },
      "beta": 1.4174
    },
    {
      "pos": {
        "x": 468.42,
        "y": 1.16
      },
      "beta": 0.2124
    },
    {
      "pos": {
        "x": 389.96,
        "y": 16.34
      },
      "beta": 3.9807
    },
    {
      "pos": {
        "x": 168.16,
        "y": 27.64
      },
      "beta": 6.1478
    },
    {
      "pos": {
        "x": 160.54,
        "y": 15.26
      },
      "beta": 2.6218
    },
    {
      "pos": {
        "x": 412.72,
        "y": 18.53
      },
      "beta": 4.4509
    },
    {
      "pos": {
        "x": 405.12,
        "y": 9.34
      },
      "beta": 2.9131
    },
    {
      "pos": {
        "x": 398.1,
        "y": 70.01
      },
      "beta": 3.8243
    },
    {
      "pos": {
        "x": 111.68,
        "y": 35.17
      },
      "beta": 2.91
    },
    {
      "pos": {
        "x": 38.39,
        "y": 6.04
      },
      "beta": 5.9122
    },
    {
      "pos": {
        "x": 452.89,
        "y": 69.7
      },
      "beta": 4.5283
    },
    {
      "pos": {
        "x": 436.37,
        "y": 31.74
      },
      "beta": 4.7234
    },
    {
      "pos": {
        "x": 493.36,
        "y": 15.29
      },
      "beta": 0.2091
    },
    {
      "pos": {
        "x": 490.63,
        "y": 24.88
      },
      "beta": 5.0663
    },
    {
      "pos": {
        "x": 197.64,
        "y": 12.46
      },
      "beta": 1.1919
    },
    {
      "pos": {
        "x": 337.06,
        "y": 4.1
      },
      "beta": 4.7863
    },
    {
      "pos": {
        "x": 352.58,
        "y": 0.26
      },
      "beta": 4.7993
    },
    {
      "pos": {
        "x": 14.75,
        "y": 99.69
      },
      "beta": 5.8891
    },
    {
      "pos": {
        "x": 345.81,
        "y": 42.46
      },
      "beta": 4.0943
    },
    {
      "pos": {
        "x": 154.0,
        "y": 86.97
      },
      "beta": 4.4511
    },
    {
      "pos": {
        "x": 222.37,
        "y": 95.38
      },
      "beta": 1.9338
    },
    {
      "pos": {
        "x": 433.82,
        "y": 15.93
      },
      "beta": 3.476
    },
    {
      "pos": {
        "x": 56.7,
        "y": 42.55
      },
      "beta": 2.0726
    },
    {
      "pos": {
        "x": 148.03,
        "y": 12.64
      },
      "beta": 0.7745
    },
    {
      "pos": {
        "x": 61.79,
        "y": 82.66
      },
      "beta": 6.2773
    },
    {
      "pos": {
        "x": 132.99,
        "y": 58.77
      },
      "beta": 5.0502
    },
    {
      "pos": {
        "x": 178.3,
        "y": 21.81
      },
      "beta": 5.7424
    },
    {
      "pos": {
        "x": 147.45,
        "y": 71.25
      },
      "beta": 2.1457
    },
    {
      "pos": {
        "x": 27.92,
        "y": 65.17
      },
      "beta": 1.5754
    },
    {
      "pos": {
        "x": 338.98,
        "y": 1.02
      },
      "beta": 1.3737
    },
    {
      "pos": {
        "x": 495.25,
        "y": 84.71
      },
      "beta": 4.9204
    },
    {
      "pos": {
        "x": 188.74,
        "y": 58.65
      },
      "beta": 5.0019
    },
    {
      "pos": {
        "x": 64.71,
        "y": 35.7
      },
      "beta": 2.0912
    },
    {
      "pos": {
        "x": 236.36,
        "y": 59.22
      },
      "beta": 1.1885
    },
    {
      "pos": {
        "x": 345.57,
        "y": 45.48
      },
      "beta": 4.1669
    },
    {
      "pos": {
        "x": 225.63,
        "y": 43.46
      },
      "beta": 3.19
    },
    {
      "pos": {
        "x": 335.34,
        "y": 44.41
      },
      "beta": 0.8063
    },
    {
      "pos": {
        "x": 386.83,
        "y": 48.23
      },
      "beta": 5.8901
    },
    {
      "pos": {
        "x": 450.92,
        "y": 10.73
      },
      "beta": 4.3343
    },
    {
      "pos": {
        "x": 50.55,
        "y": 4.61
      },
      "beta": 3.4396
    },
    {
      "pos": {
        "x": 284.8,
        "y": 59.85
      },
      "beta": 5.7907
    },
    {
      "pos": {
        "x": 202.58,
        "y": 62.43
      },
      "beta": 3.4923
    },
    {
      "pos": {
        "x": 324.52,
        "y": 23.64
      },
      "beta": 0.6266
    },
    {
      "pos": {
        "x": 431.2,
        "y": 17.04
      },
      "beta": 5.5608
    },
    {
      "pos": {
        "x": 62.38,
        "y": 13.4
      },
      "beta": 6.0118
    },
    {
      "pos": {
        "x": 352.29,
        "y": 68.26
      },
      "beta": 4.7565
    },
    {
      "pos": {
        "x": 365.69,
        "y": 62.39
      },
      "beta": 4.5224
    },
    {
      "pos": {
        "x": 83.3,
        "y": 74.62
      },
      "beta": 4.6826
    },
    {
      "pos": {
        "x": 45.39,
        "y": 59.41
      },
      "beta": 5.5053
    },
    {
      "pos": {
        "x": 378.74,
        "y": 42.05
      },
      "beta": 3.5211
    },
    {
      "pos": {
        "x": 88.59,
        "y": 59.83
      },
      "beta": 2.4462
    },
    {
      "pos": {
        "x": 155.3,
        "y": 8.51
      },
      "beta": 5.9285
    },
    {
      "pos": {
        "x": 493.73,
        "y": 74.18
      },
      "beta": 2.5936
    },
    {
      "pos": {
        "x": 126.85,
        "y": 92.52
      },
      "beta": 4.962
    },
    {
      "pos": {
        "x": 207.33,
        "y": 21.63
      },
      "beta": 5.0264
    },
    {
      "pos": {
        "x": 151.68,
        "y": 9.46
      },
      "beta": 1.4649
    },
    {
      "pos": {
        "x": 492.16,
        "y": 34.55
      },
      "beta": 4.7179
    },
    {
      "pos": {
        "x": 437.67,
        "y": 52.96
      },
      "beta": 2.2521
    },
    {
      "pos": {
        "x": 199.95,
        "y": 31.15
      },
      "beta": 2.2475
    },
    {
      "pos": {
        "x": 249.89,
        "y": 22.6
      },
      "beta": 2.0369
    },
    {
      "pos": {
        "x": 143.85,
        "y": 77.7
      },
      "beta": 0.5051
    },
    {
      "pos": {
        "x": 396.82,
        "y": 53.3
      },
      "beta": 4.2249
    },
    {
      "pos": {
        "x": 359.0,
        "y": 87.78
      },
      "beta": 2.7001
    },
    {
      "pos": {
        "x": 215.76,
        "y": 31.39
      },
      "beta": 1.9148
    },
    {
      "pos": {
        "x": 223.05,
        "y": 24.14
      },
      "beta": 3.3511
    },
    {
      "pos": {
        "x": 236.35,
        "y": 44.0
      },
      "beta": 3.7054
    },
    {
      "pos": {
        "x": 78.36,
        "y": 56.9
      },
      "beta": 2.9626
    },
    {
      "pos": {
        "x": 441.0,
        "y": 26.42
      },
      "beta": 5.9429
    },
    {
      "pos": {
        "x": 385.86,
        "y": 20.49
      },
      "beta": 3.1456
    },
    {
      "pos": {
        "x": 116.56,
        "y": 85.14
      },
      "beta": 3.2313
    },
    {
      "pos": {
        "x": 46.55,
        "y": 21.01
      },
      "beta": 0.6792
    },
    {
      "pos": {
        "x": 216.98,
        "y": 13.64
      },
      "beta": 5.0304
    },
    {
      "pos": {
        "x": 44.56,
        "y": 11.17
      },
      "beta": 1.2573
    },
    {
      "pos": {
        "x": 236.4,
        "y": 21.54
      },
      "beta": 0.1787
    },
    {
      "pos": {
        "x": 170.61,
        "y": 79.38
      },
      "beta": 3.379
    },
    {
      "pos": {
        "x": 300.47,
        "y": 0.11
      },
      "beta": 3.1144
    },
    {
      "pos": {
        "x": 20.84,
        "y": 57.48
      },
      "beta": 1.5595
    },
    {
      "pos": {
        "x": 472.79,
        "y": 79.21
      },
      "beta": 0.9016
    },
    {
      "pos": {
        "x": 217.8,
        "y": 1.92
      },
      "beta": 2.6148
    },
    {
      "pos": {
        "x": 209.87,
        "y": 40.83
      },
      "beta": 1.4638
    },
    {
      "pos": {
        "x": 417.17,
        "y": 58.35
      },
      "beta": 3.2182
    },
    {
      "pos": {
        "x": 407.56,
        "y": 18.13
      },
      "beta": 0.3852
    },
    {
      "pos": {
        "x": 71.78,
        "y": 88.19
      },
      "beta": 1.33
    },
    {
      "pos": {
        "x": 499.02,
        "y": 1.93
      },
      "beta": 3.0849
    },
    {
      "pos": {
        "x": 260.38,
        "y": 7.19
      },
      "beta": 5.3746
    },
    {
      "pos": {
        "x": 407.7,
        "y": 60.42
      },
      "beta": 5.3784
    },
    {
      "pos": {
        "x": 78.7,
        "y": 60.96
      },
      "beta": 1.0434
    },
    {
      "pos": {
        "x": 125.4,
        "y": 63.27
      },
      "beta": 1.8674
    },
    {
      "pos": {
        "x": 66.66,
        "y": 77.36
      },
      "beta": 2.2095
    },
    {
      "pos": {
        "x": 253.35,
        "y": 34.18
      },
      "beta": 2.339
    },
    {
      "pos": {
        "x": 439.36,
        "y": 69.76
      },
      "beta": 4.8328
    },
    {
      "pos": {
        "x": 479.74,
        "y": 95.72
      },
      "beta": 1.1103
    },
    {
      "pos": {
        "x": 428.04,
        "y": 48.05
      },
      "beta": 4.3191
    },
    {
      "pos": {
        "x": 100.02,
        "y": 41.0
      },
      "beta": 0.5866
    },
    {
      "pos": {
        "x": 131.6,
        "y": 12.09
      },
      "beta": 5.6926
    },
    {
      "pos": {
        "x": 217.96,
        "y": 87.1
      },
      "beta": 6.2655
    },
    {
      "pos": {
        "x": 39.71,
        "y": 88.23
      },
      "beta": 1.2558
    },
    {
      "pos": {
        "x": 68.86,
        "y": 38.35
      },
      "beta": 0.4013
    },
    {
      "pos": {
        "x": 94.79,
        "y": 47.89
      },
      "beta": 3.7452
    },
    {
      "pos": {
        "x": 349.76,
        "y": 87.68
      },
      "beta": 5.4912
    },
    {
      "pos": {
        "x": 174.84,
        "y": 33.71
      },
      "beta": 0.3747
    },
    {
      "pos": {
        "x": 211.74,
        "y": 17.4
      },
      "beta": 5.2886
    },
    {
      "pos": {
        "x": 457.2,
        "y": 53.99
      },
      "beta": 2.4353
    },
    {
      "pos": {
        "x": 107.26,
        "y": 16.66
      },
      "beta": 6.245
    },
    {
      "pos": {
        "x": 330.49,
        "y": 74.89
      },
      "beta": 4.5525
    },
    {
      "pos": {
        "x": 165.14,
        "y": 46.69
      },
      "beta": 5.6391
    },
    {
      "pos": {
        "x": 241.25,
        "y": 49.82
      },
      "beta": 6.2574
    },
    {
      "pos": {
        "x": 477.12,
        "y": 20.6
      },
      "beta": 6.1047
    },
    {
      "pos": {
        "x": 120.6,
        "y": 97.54
      },
      "beta": 5.108
    },
    {
      "pos": {
        "x": 5.04,
        "y": 90.49
      },
      "beta": 3.9608
    },
    {
      "pos": {
        "x": 85.91,
        "y": 82.72
      },
      "beta": 5.3212
    },
    {
      "pos": {
        "x": 130.94,
        "y": 15.65
      },
      "beta": 2.1093
    },
    {
      "pos": {
        "x": 385.09,
        "y": 71.89
      },
      "beta": 5.7333
    },
    {
      "pos": {
        "x": 142.62,
        "y": 10.83
      },
      "beta": 2.8534
    },
    {
      "pos": {
        "x": 335.88,
        "y": 83.97
      },
      "beta": 0.182
    },
    {
      "pos": {
        "x": 229.54,
        "y": 78.71
      },
      "beta": 5.863
    },
    {
      "pos": {
        "x": 141.29,
        "y": 42.5
      },
      "beta": 4.6995
    },
    {
      "pos": {
        "x": 184.81,
        "y": 99.11
      },
      "beta": 3.1547
    },
    {
      "pos": {
        "x": 65.21,
        "y": 24.74
      },
      "beta": 2.3437
    },
    {
      "pos": {
        "x": 342.95,
        "y": 36.08
      },
      "beta": 4.2517
    },
    {
      "pos": {
        "x": 211.01,
        "y": 85.61
      },
      "beta": 2.0495
    },
    {
      "pos": {
        "x": 237.73,
        "y": 31.44
      },
      "beta": 3.5387
    },
    {
      "pos": {
        "x": 369.25,
        "y": 65.6
      },
      "beta": 0.7287
    },
    {
      "pos": {
        "x": 472.34,
        "y": 59.83
      },
      "beta": 3.4543
    },
    {
      "pos": {
        "x": 119.43,
        "y": 83.65
      },
      "beta": 2.8878
    },
    {
      "pos": {
        "x": 33.48,
        "y": 91.4
      },
      "beta": 2.3055
    },
    {
      "pos": {
        "x": 360.44,
        "y": 73.26
      },
      "beta": 4.7238
    },
    {
      "pos": {
        "x": 220.93,
        "y": 31.66
      },
      "beta": 4.7519
    },
    {
      "pos": {
        "x": 442.46,
        "y": 2.82
      },
      "beta": 0.6636
    },
    {
      "pos": {
        "x": 35.38,
        "y": 84.76
      },
      "beta": 0.211
    },
    {
      "pos": {
        "x": 410.04,
        "y": 10.05
      },
      "beta": 1.6845
    },
    {
      "pos": {
        "x": 474.72,
        "y": 27.94
      },
      "beta": 5.3864
    },
    {
      "pos": {
        "x": 208.17,
        "y": 92.73
      },
      "beta": 1.4328
    },
    {
      "pos": {
        "x": 36.23,
        "y": 92.19
      },
      "beta": 0.106
    },
    {
      "pos": {
        "x": 300.25,
        "y": 65.28
      },
      "beta": 1.4249
    },
    {
      "pos": {
        "x": 287.26,
        "y": 7.35
      },
      "beta": 2.3255
    },
    {
      "pos": {
        "x": 175.12,
        "y": 31.71
      },
      "beta": 0.9554
    },
    {
      "pos": {
        "x": 217.81,
        "y": 91.83
      },
      "beta": 1.0279
    },
    {
      "pos": {
        "x": 222.42,
        "y": 21.07
      },
      "beta": 2.9222
    },
    {
      "pos": {
        "x": 481.1,
        "y": 72.97
      },
      "beta": 5.1698
    },
    {
      "pos": {
        "x": 241.57,
        "y": 5.6
      },
      "beta": 3.8052
    },
    {
      "pos": {
        "x": 299.64,
        "y": 20.81
      },
      "beta": 2.5934
    },
    {
      "pos": {
        "x": 388.63,
        "y": 72.57
      },
      "beta": 3.0183
    },
    {
      "pos": {
        "x": 29.84,
        "y": 39.02
      },
      "beta": 5.5353
    },
    {
      "pos": {
        "x": 119.19,
        "y": 70.66
      },
      "beta": 6.0575
    },
    {
      "pos": {
        "x": 136.29,
        "y": 82.71
      },
      "beta": 3.0807
    },
    {
      "pos": {
        "x": 199.24,
        "y": 3.45
      },
      "beta": 4.3854
    },
    {
      "pos": {
        "x": 309.43,
        "y": 87.31
      },
      "beta": 4.9005
    },
    {
      "pos": {
        "x": 227.61,
        "y": 62.13
      },
      "beta": 3.7331
    },
    {
      "pos": {
        "x": 43.7,
        "y": 82.95
      },
      "beta": 0.1737
    },
    {
      "pos": {
        "x": 489.11,
        "y": 90.98
      },
      "beta": 2.8351
    },
    {
      "pos": {
        "x": 118.73,
        "y": 0.46
      },
      "beta": 4.6441
    },
    {
      "pos": {
        "x": 439.71,
        "y": 10.57
      },
      "beta": 2.8346
    },
    {
      "pos": {
        "x": 179.66,
        "y": 32.88
      },
      "beta": 0.7872
    },
    {
      "pos": {
        "x": 286.65,
        "y": 23.19
      },
      "beta": 5.6657
    },
    {
      "pos": {
        "x": 187.11,
        "y": 81.6
      },
      "beta": 0.693
    },
    {
      "pos": {
        "x": 270.55,
        "y": 28.78
      },
      "beta": 6.0007
    },
    {
      "pos": {
        "x": 383.68,
        "y": 56.01
      },
      "beta": 4.1994
    },
    {
      "pos": {
        "x": 87.79,
        "y": 33.29
      },
      "beta": 3.1058
    },
    {
      "pos": {
        "x": 73.76,
        "y": 69.77
      },
      "beta": 1.7741
    },
    {
      "pos": {
        "x": 327.62,
        "y": 20.77
      },
      "beta": 2.5393
    },
    {
      "pos": {
        "x": 460.96,
        "y": 88.02
      },
      "beta": 6.0667
    },
    {
      "pos": {
        "x": 454.35,
        "y": 87.78
      },
      "beta": 0.6888
    },
    {
      "pos": {
        "x": 171.06,
        "y": 1.39
      },
      "beta": 3.4524
    },
    {
      "pos": {
        "x": 319.61,
        "y": 65.41
      },
      "beta": 1.0898
    },
    {
      "pos": {
        "x": 166.07,
        "y": 29.13
      },
      "beta": 3.6584
    },
    {
      "pos": {
        "x": 223.3,
        "y": 40.88
      },
      "beta": 2.0141
    },
    {
      "pos": {
        "x": 487.91,
        "y": 35.65
      },
      "beta": 1.3961
    },
    {
      "pos": {
        "x": 100.54,
        "y": 45.97
      },
      "beta": 3.5425
    },
    {
      "pos": {
        "x": 198.6,
        "y": 13.39
      },
      "beta": 4.6379
    },
    {
      "pos": {
        "x": 406.42,
        "y": 50.2
      },
      "beta": 1.7083
    },
    {
      "pos": {
        "x": 212.42,
        "y": 90.4
      },
      "beta": 3.1788
    },
    {
      "pos": {
        "x": 22.68,
        "y": 12.69
      },
      "beta": 3.3234
    },
    {
      "pos": {
        "x": 252.76,
        "y": 63.0
      },
      "beta": 0.4529
    },
    {
      "pos": {
        "x": 375.44,
        "y": 46.35
      },
      "beta": 5.5797
    },
    {
      "pos": {
        "x": 472.26,
        "y": 15.77
      },
      "beta": 0.1584
    },
    {
      "pos": {
        "x": 431.53,
        "y": 0.0
      },
      "beta": 4.5978
    },
    {
      "pos": {
        "x": 83.0,
        "y": 11.65
      },
      "beta": 2.9458
    },
    {
      "pos": {
        "x": 272.01,
        "y": 99.4
      },
      "beta": 2.8293
    },
    {
      "pos": {
        "x": 70.83,
        "y": 57.93
      },
      "beta": 2.0997
    },
    {
      "pos": {
        "x": 276.73,
        "y": 39.9
      },
      "beta": 4.6649
    },
    {
      "pos": {
        "x": 217.98,
        "y": 53.26
      },
      "beta": 1.8933
    },
    {
      "pos": {
        "x": 478.18,
        "y": 49.44
      },
      "beta": 0.7719
    },
    {
      "pos": {
        "x": 461.35,
        "y": 90.01
      },
      "beta": 6.2238
    },
    {
      "pos": {
        "x": 46.14,
        "y": 70.85
      },
      "beta": 5.659
    },
    {
      "pos": {
        "x": 118.24,
        "y": 84.65
      },
      "beta": 0.3271
    },
    {
      "pos": {
        "x": 307.87,
        "y": 51.45
      },
      "beta": 0.574
    },
    {
      "pos": {
        "x": 34.7,
        "y": 97.36
      },
      "beta": 4.2504
    },
    {
      "pos": {
        "x": 35.92,
        "y": 76.85
      },
      "beta": 0.128
    },
    {
      "pos": {
        "x": 382.8,
        "y": 80.38
      },
      "beta": 1.7448
    },
    {
      "pos": {
        "x": 164.62,
        "y": 24.28
      },
      "beta": 4.4734
    },
    {
      "pos": {
        "x": 430.26,
        "y": 41.5
      },
      "beta": 5.6685
    },
    {
      "pos": {
        "x": 7.88,
        "y": 95.18
      },
      "beta": 0.1493
    },
    {
      "pos": {
        "x": 339.56,
        "y": 28.28
      },
      "beta": 1.1652
    },
    {
      "pos": {
        "x": 225.77,
        "y": 32.8
      },
      "beta": 6.0866
    },
    {
      "pos": {
        "x": 77.25,
        "y": 99.51
      },
      "beta": 3.1453
    },
    {
      "pos": {
        "x": 279.3,
        "y": 35.04
      },
      "beta": 2.5279
    },
    {
      "pos": {
        "x": 270.19,
        "y": 40.01
      },
      "beta": 3.9312
    },
    {
      "pos": {
        "x": 298.55,
        "y": 60.06
      },
      "beta": 6.0654
    },
    {
      "pos": {
        "x": 284.14,
        "y": 21.91
      },
      "beta": 4.4029
    },
    {
      "pos": {
        "x": 179.88,
        "y": 36.6
      },
      "beta": 2.7124
    },
    {
      "pos": {
        "x": 452.39,
        "y": 42.99
      },
      "beta": 3.9532
    },
    {
      "pos": {
        "x": 227.29,
        "y": 6.42
      },
      "beta": 5.8343
    },
    {
      "pos": {
        "x": 279.14,
        "y": 23.81
      },
      "beta": 5.0352
    },
    {
      "pos": {
        "x": 257.57,
        "y": 12.23
      },
      "beta": 1.9466
    },
    {
      "pos": {
        "x": 77.55,
        "y": 19.54
      },
      "beta": 2.8605
    },
    {
      "pos": {
        "x": 304.92,
        "y": 50.41
      },
      "beta": 1.5903
    },
    {
      "pos": {
        "x": 351.8,
        "y": 73.3
      },
      "beta": 2.5627
    },
    {
      "pos": {
        "x": 354.64,
        "y": 96.25
      },
      "beta": 3.3448
    },
    {
      "pos": {
        "x": 435.06,
        "y": 38.17
      },
      "beta": 4.9005
    },
    {
      "pos": {
        "x": 466.38,
        "y": 75.3
      },
      "beta": 1.9693
    },
    {
      "pos": {
        "x": 16.79,
        "y": 77.3
      },
      "beta": 3.6783
    },
    {
      "pos": {
        "x": 95.94,
        "y": 52.24
      },
      "beta": 2.2594
    },
    {
      "pos": {
        "x": 430.26,
        "y": 63.1
      },
      "beta": 1.0949
    },
    {
      "pos": {
        "x": 418.87,
        "y": 88.28
      },
      "beta": 3.2485
    },
    {
      "pos": {
        "x": 121.32,
        "y": 26.39
      },
      "beta": 5.1339
    },
    {
      "pos": {
        "x": 57.83,
        "y": 2.93
      },
      "beta": 2.0029
    },
    {
      "pos": {
        "x": 124.66,
        "y": 40.44
      },
      "beta": 0.9113
    },
    {
      "pos": {
        "x": 331.21,
        "y": 86.64
      },
      "beta": 5.0267
    },
    {
      "pos": {
        "x": 474.87,
        "y": 34.0
      },
      "beta": 0.2961
    },
    {
      "pos": {
        "x": 20.56,
        "y": 42.42
      },
      "beta": 1.2609
    },
    {
      "pos": {
        "x": 356.45,
        "y": 4.99
      },
      "beta": 6.1522
    },
    {
      "pos": {
        "x": 138.72,
        "y": 32.84
      },
      "beta": 3.7542
    },
    {
      "pos": {
        "x": 4.59,
        "y": 84.23
      },
      "beta": 5.0754
    },
    {
      "pos": {
        "x": 69.51,
        "y": 63.01
      },
      "beta": 1.1341
    },
    {
      "pos": {
        "x": 351.65,
        "y": 39.03
      },
      "beta": 5.448
    },
    {
      "pos": {
        "x": 228.88,
        "y": 81.02
      },
      "beta": 1.4645
    },
    {
      "pos": {
        "x": 241.4,
        "y": 40.32
      },
      "beta": 0.7007
    },
    {
      "pos": {
        "x": 406.13,
        "y": 30.24
      },
      "beta": 2.3626
    },
    {
      "pos": {
        "x": 149.71,
        "y": 20.41
      },
      "beta": 2.3574
    },
    {
      "pos": {
        "x": 40.61,
        "y": 84.74
      },
      "beta": 1.5279
    }
  ]
}